[{"model": "poi_manager.poicategory", "pk": 1, "fields": {"cat_name": "wifi", "icon_css_name": "", "fk_poi_icon": null, "description": "access point wifi", "force_mid_point": null, "enabled": null, "tree_order": null, "sort_order": null, "parent": null, "lft": 1, "rght": 2, "tree_id": 1, "level": 0}}, {"model": "poi_manager.poicategory", "pk": 2, "fields": {"cat_name": "food and beverages", "icon_css_name": "", "fk_poi_icon": null, "description": "", "force_mid_point": null, "enabled": null, "tree_order": null, "sort_order": null, "parent": null, "lft": 1, "rght": 8, "tree_id": 2, "level": 0}}, {"model": "poi_manager.poicategory", "pk": 3, "fields": {"cat_name": "coffee shop", "icon_css_name": "", "fk_poi_icon": null, "description": "", "force_mid_point": null, "enabled": null, "tree_order": null, "sort_order": null, "parent": 2, "lft": 2, "rght": 3, "tree_id": 2, "level": 1}}, {"model": "poi_manager.poicategory", "pk": 4, "fields": {"cat_name": "education", "icon_css_name": "", "fk_poi_icon": null, "description": "", "force_mid_point": null, "enabled": null, "tree_order": null, "sort_order": null, "parent": null, "lft": 1, "rght": 2, "tree_id": 3, "level": 0}}, {"model": "poi_manager.poicategory", "pk": 5, "fields": {"cat_name": "transportation", "icon_css_name": "", "fk_poi_icon": null, "description": "", "force_mid_point": null, "enabled": null, "tree_order": null, "sort_order": null, "parent": null, "lft": 1, "rght": 8, "tree_id": 4, "level": 0}}, {"model": "poi_manager.poicategory", "pk": 6, "fields": {"cat_name": "taxi", "icon_css_name": "", "fk_poi_icon": null, "description": "", "force_mid_point": null, "enabled": null, "tree_order": null, "sort_order": null, "parent": 5, "lft": 2, "rght": 3, "tree_id": 4, "level": 1}}, {"model": "poi_manager.poicategory", "pk": 7, "fields": {"cat_name": "bus", "icon_css_name": "", "fk_poi_icon": null, "description": "", "force_mid_point": null, "enabled": null, "tree_order": null, "sort_order": null, "parent": 5, "lft": 4, "rght": 5, "tree_id": 4, "level": 1}}, {"model": "poi_manager.poicategory", "pk": 8, "fields": {"cat_name": "underground", "icon_css_name": "", "fk_poi_icon": null, "description": "", "force_mid_point": null, "enabled": null, "tree_order": null, "sort_order": null, "parent": null, "lft": 1, "rght": 2, "tree_id": 5, "level": 0}}, {"model": "poi_manager.poicategory", "pk": 9, "fields": {"cat_name": "train", "icon_css_name": "", "fk_poi_icon": null, "description": "", "force_mid_point": null, "enabled": null, "tree_order": null, "sort_order": null, "parent": 5, "lft": 6, "rght": 7, "tree_id": 4, "level": 1}}, {"model": "poi_manager.poicategory", "pk": 10, "fields": {"cat_name": "", "icon_css_name": "", "fk_poi_icon": null, "description": "", "force_mid_point": null, "enabled": null, "tree_order": null, "sort_order": null, "parent": null, "lft": 1, "rght": 2, "tree_id": 6, "level": 0}}, {"model": "poi_manager.poicategory", "pk": 11, "fields": {"cat_name": "restaurant", "icon_css_name": "", "fk_poi_icon": null, "description": "", "force_mid_point": null, "enabled": null, "tree_order": null, "sort_order": null, "parent": 2, "lft": 4, "rght": 5, "tree_id": 2, "level": 1}}, {"model": "poi_manager.poicategory", "pk": 12, "fields": {"cat_name": "vending machine", "icon_css_name": "", "fk_poi_icon": null, "description": "", "force_mid_point": null, "enabled": null, "tree_order": null, "sort_order": null, "parent": 2, "lft": 6, "rght": 7, "tree_id": 2, "level": 1}}, {"model": "poi_manager.poicategory", "pk": 13, "fields": {"cat_name": "parking", "icon_css_name": "", "fk_poi_icon": null, "description": "", "force_mid_point": null, "enabled": null, "tree_order": null, "sort_order": null, "parent": null, "lft": 1, "rght": 10, "tree_id": 7, "level": 0}}, {"model": "poi_manager.poicategory", "pk": 14, "fields": {"cat_name": "bike", "icon_css_name": "", "fk_poi_icon": null, "description": "", "force_mid_point": null, "enabled": null, "tree_order": null, "sort_order": null, "parent": 13, "lft": 2, "rght": 3, "tree_id": 7, "level": 1}}, {"model": "poi_manager.poicategory", "pk": 15, "fields": {"cat_name": "motor bike", "icon_css_name": "", "fk_poi_icon": null, "description": "", "force_mid_point": null, "enabled": null, "tree_order": null, "sort_order": null, "parent": 13, "lft": 4, "rght": 5, "tree_id": 7, "level": 1}}, {"model": "poi_manager.poicategory", "pk": 16, "fields": {"cat_name": "car", "icon_css_name": "", "fk_poi_icon": null, "description": "", "force_mid_point": null, "enabled": null, "tree_order": null, "sort_order": null, "parent": 13, "lft": 6, "rght": 7, "tree_id": 7, "level": 1}}, {"model": "poi_manager.poicategory", "pk": 17, "fields": {"cat_name": "bike covered", "icon_css_name": "", "fk_poi_icon": null, "description": "", "force_mid_point": null, "enabled": null, "tree_order": null, "sort_order": null, "parent": 13, "lft": 8, "rght": 9, "tree_id": 7, "level": 1}}]